betterlogging/__init__.py
betterlogging/blogging.py
prettysimplelogging-0.2.0.dist-info/licenses/LICENSE
prettysimplelogging-0.2.0.dist-info/METADATA
prettysimplelogging-0.2.0.dist-info/WHEEL
prettysimplelogging-0.2.0.dist-info/top_level.txt
prettysimplelogging-0.2.0.dist-info/RECORD
