Metadata-Version: 2.4
Name: prettysimplelogging
Version: 0.2.0
Summary: Better Logging
Author-email: Regan Willis <reganwillis@outlook.com>
License-Expression: MIT
Project-URL: Homepage, https://github.com/reganwillis/BetterLogging
License-File: LICENSE
Requires-Dist: rich
Dynamic: license-file
